forgeapp_sdk/__init__.py
forgeapp_sdk/classes/__init__.py
forgeapp_sdk/classes/action.py
forgeapp_sdk/classes/component.py
forgeapp_sdk/classes/forge_file.py
forgeapp_sdk/classes/io.py
forgeapp_sdk/classes/io_client.py
forgeapp_sdk/classes/io_error.py
forgeapp_sdk/classes/io_promise.py
forgeapp_sdk/classes/isocket.py
forgeapp_sdk/classes/layout.py
forgeapp_sdk/classes/logger.py
forgeapp_sdk/classes/page.py
forgeapp_sdk/classes/rpc.py
forgeapp_sdk/classes/transaction_loading_state.py
forgeapp_sdk/components/__init__.py
forgeapp_sdk/components/grid.py
forgeapp_sdk/components/table.py
forgeapp_sdk/handlers.py
forgeapp_sdk/internal_rpc_schema.py
forgeapp_sdk/io_schema.py
forgeapp_sdk/main.py
forgeapp_sdk/superjson/__init__.py
forgeapp_sdk/superjson/main.py
forgeapp_sdk/superjson/plainer.py
forgeapp_sdk/superjson/tests/__init__.py
forgeapp_sdk/superjson/tests/node-only-types.js
forgeapp_sdk/superjson/tests/round-trip-superjson.js
forgeapp_sdk/superjson/tests/test_superjson.py
forgeapp_sdk/superjson/transformer.py
forgeapp_sdk/types.py
forgeapp_sdk/util.py
forgeapp_sdk-0.2.0.dist-info/METADATA
forgeapp_sdk-0.2.0.dist-info/WHEEL
forgeapp_sdk-0.2.0.dist-info/RECORD
