Metadata-Version: 2.1
Name: forgeapp-sdk
Version: 0.2.0
Summary: Forge python SDK
Home-page: https://forgeapp.io
Keywords: internal tool,app,ui,ui builder
Author: Rambo
Author-email: rambo@forgeapp.io
Maintainer: Rambo
Maintainer-email: rambo@forgeapp.io
Requires-Python: >=3.9,<4.0
Classifier: Programming Language :: Python :: 3
Classifier: Programming Language :: Python :: 3.9
Classifier: Programming Language :: Python :: 3.10
Classifier: Programming Language :: Python :: 3.11
Classifier: Programming Language :: Python :: 3.12
Classifier: Programming Language :: Python :: 3.13
Requires-Dist: aiodns (>=3.0.0,<4.0.0)
Requires-Dist: aiohttp (>=3.10.10,<4.0.0)
Requires-Dist: pydantic (>=1.9.0,<2.0.0)
Requires-Dist: typing-extensions (>=4.4.0,<5.0.0)
Requires-Dist: websockets (>=10.1,<11.0)
Project-URL: Documentation, https://docs.forgeapp.io/
